MANIFEST.in
README.rst
setup.py
src/unpushed/__init__.py
src/unpushed/command.py
src/unpushed/logo.png
src/unpushed/notify.py
src/unpushed/repos.py
src/unpushed/scanner.py
src/unpushed.egg-info/PKG-INFO
src/unpushed.egg-info/SOURCES.txt
src/unpushed.egg-info/dependency_links.txt
src/unpushed.egg-info/entry_points.txt
src/unpushed.egg-info/top_level.txt