Metadata-Version: 1.1
Name: unpushed
Version: 1.1.0
Summary: Scan version control for uncommitted and unpushed changes
Home-page: http://github.com/nailgun/unpushed/
Author: Dmitry Bashkatov
Author-email: dbashkatov@gmail.com
License: UNKNOWN
Platform: UNKNOWN
Classifier: Development Status :: 4 - Beta
Classifier: Environment :: Console
Classifier: Intended Audience :: Developers
Classifier: License :: OSI Approved :: MIT License
Classifier: Topic :: Software Development :: Version Control
Classifier: Topic :: Utilities
